{"stat.pickup.minecraft.diamond_leggings":1,"stat.useItem.minecraft.golden_apple":4,"stat.flyOneCm":10588,"stat.walkOneCm":12039,"stat.pickup.betteranimalsplus.wolf_pelt_brown":1,"stat.jump":10,"stat.playOneMinute":2555,"stat.fallOneCm":484,"stat.pickup.betteranimalsplus.wolfhead_6":1,"stat.pickup.minecraft.diamond_helmet":1,"stat.damageTaken":441,"stat.damageDealt":99,"stat.timeSinceDeath":2555,"stat.pickup.minecraft.diamond_chestplate":1,"stat.sprintOneCm":1257,"stat.pickup.minecraft.diamond_boots":1,"stat.useItem.minecraft.spawn_egg":2}